CONTRIBUTING.md
MANIFEST.in
README.rst
setup.py
docs/HISTORY.txt
docs/LICENSE.GPL
docs/LICENSE.txt
eea/__init__.py
eea.api.layout.egg-info/PKG-INFO
eea.api.layout.egg-info/SOURCES.txt
eea.api.layout.egg-info/dependency_links.txt
eea.api.layout.egg-info/entry_points.txt
eea.api.layout.egg-info/namespace_packages.txt
eea.api.layout.egg-info/not-zip-safe
eea.api.layout.egg-info/requires.txt
eea.api.layout.egg-info/top_level.txt
eea/api/__init__.py
eea/api/layout/README.txt
eea/api/layout/__init__.py
eea/api/layout/configure.zcml
eea/api/layout/interfaces.py
eea/api/layout/profiles.zcml
eea/api/layout/setuphandlers.py
eea/api/layout/version.txt
eea/api/layout/behaviors/__init__.py
eea/api/layout/behaviors/configure.zcml
eea/api/layout/browser/__init__.py
eea/api/layout/browser/configure.zcml
eea/api/layout/browser/controlpanel.py
eea/api/layout/layout/__init__.py
eea/api/layout/layout/configure.zcml
eea/api/layout/layout/get.py
eea/api/layout/locales/__init__.py
eea/api/layout/locales/eea.pot
eea/api/layout/locales/plone-manual.pot
eea/api/layout/locales/update.sh
eea/api/layout/locales/bg/LC_MESSAGES/eea.po
eea/api/layout/locales/bg/LC_MESSAGES/plone.po
eea/api/layout/locales/cs/LC_MESSAGES/eea.po
eea/api/layout/locales/cs/LC_MESSAGES/plone.po
eea/api/layout/locales/da/LC_MESSAGES/eea.po
eea/api/layout/locales/da/LC_MESSAGES/plone.po
eea/api/layout/locales/de/LC_MESSAGES/eea.po
eea/api/layout/locales/de/LC_MESSAGES/plone.po
eea/api/layout/locales/el/LC_MESSAGES/eea.po
eea/api/layout/locales/el/LC_MESSAGES/plone.po
eea/api/layout/locales/en/LC_MESSAGES/eea.po
eea/api/layout/locales/en/LC_MESSAGES/plone.po
eea/api/layout/locales/es/LC_MESSAGES/eea.po
eea/api/layout/locales/es/LC_MESSAGES/plone.po
eea/api/layout/locales/et/LC_MESSAGES/eea.po
eea/api/layout/locales/et/LC_MESSAGES/plone.po
eea/api/layout/locales/eu/LC_MESSAGES/eea.po
eea/api/layout/locales/eu/LC_MESSAGES/plone.po
eea/api/layout/locales/fi/LC_MESSAGES/eea.po
eea/api/layout/locales/fi/LC_MESSAGES/plone.po
eea/api/layout/locales/fr/LC_MESSAGES/eea.po
eea/api/layout/locales/fr/LC_MESSAGES/plone.po
eea/api/layout/locales/hr/LC_MESSAGES/eea.po
eea/api/layout/locales/hr/LC_MESSAGES/plone.po
eea/api/layout/locales/hu/LC_MESSAGES/eea.po
eea/api/layout/locales/hu/LC_MESSAGES/plone.po
